{
  "release": "v135",
  "featureSlug": "css-anchor-positioning-remembered-scroll-offset",
  "conceptSlug": "anchor-scroll",
  "chromestatusId": 4710507824807936,
  "reviewedAt": "2026-06-02T13:07:21Z",
  "reviewer": "codex-goal-setting",
  "rubric": {
    "spec_match": {
      "state": "pass",
      "rationale": "The page now avoids the stale position-try-options syntax and uses current anchor positioning with position-try-order: most-height."
    },
    "interactive": {
      "state": "pass",
      "rationale": "The toggle compares CSS anchor positioning with a legacy JS fallback and the scroller remains directly manipulable."
    },
    "blurb_alignment": {
      "state": "pass",
      "rationale": "The page demonstrates remembered scroll offset instead of generic anchor positioning alone."
    },
    "edge_cases": {
      "state": "pass",
      "rationale": "The page directly probes anchor support and fallback-order support while showing the legacy fallback path."
    },
    "references": {
      "state": "pass",
      "rationale": "The page links to chromestatus.com/feature/4710507824807936 and the CSS Anchor Positioning spec."
    },
    "design_system": {
      "state": "pass",
      "rationale": "The local styling uses shared CSS variables and accessible status colors."
    }
  },
  "openQuestions": [],
  "summary": "The single-scroller demo now reflects current syntax and browser support, replacing the stale most-scroll-position framing."
}
