{
  "release": "v136",
  "featureSlug": "captured-surface-control",
  "chromestatusId": 5092615678066688,
  "specUrl": "https://w3c.github.io/mediacapture-surface-control/",
  "generatedAt": "2026-06-01T08:03:56Z",
  "author": "conformance-author-v1-subagent",
  "assertions": [
    {
      "id": "capture-controller-exists",
      "description": "CaptureController is exposed — the object that brokers control of a captured tab.",
      "kind": "typeof",
      "test": "CaptureController",
      "expect": "function",
      "specSection": "https://w3c.github.io/mediacapture-surface-control/#capturecontroller"
    },
    {
      "id": "forward-wheel-is-function",
      "description": "CaptureController.prototype.forwardWheel is a function — binds trusted wheel events from an element to the captured surface.",
      "kind": "typeof",
      "test": "CaptureController.prototype.forwardWheel",
      "expect": "function",
      "specSection": "https://w3c.github.io/mediacapture-surface-control/#dom-capturecontroller-forwardwheel"
    },
    {
      "id": "get-supported-zoom-levels",
      "description": "CaptureController exposes getSupportedZoomLevels() for enumerating allowed zoom levels.",
      "kind": "typeof",
      "test": "CaptureController.prototype.getSupportedZoomLevels",
      "expect": "function",
      "specSection": "https://w3c.github.io/mediacapture-surface-control/#dom-capturecontroller-getsupportedzoomlevels"
    },
    {
      "id": "zoom-level-attribute",
      "description": "CaptureController.prototype exposes the readonly zoomLevel attribute.",
      "kind": "script",
      "test": "(()=>typeof CaptureController==='function'&&!!Object.getOwnPropertyDescriptor(CaptureController.prototype,'zoomLevel')&&typeof Object.getOwnPropertyDescriptor(CaptureController.prototype,'zoomLevel').get==='function')()",
      "specSection": "https://w3c.github.io/mediacapture-surface-control/#dom-capturecontroller-zoomlevel"
    },
    {
      "id": "increase-zoom-level-is-function",
      "description": "CaptureController.prototype.increaseZoomLevel steps the captured tab to the next supported zoom level.",
      "kind": "typeof",
      "test": "CaptureController.prototype.increaseZoomLevel",
      "expect": "function",
      "specSection": "https://w3c.github.io/mediacapture-surface-control/#dom-capturecontroller-increasezoomlevel"
    },
    {
      "id": "decrease-zoom-level-is-function",
      "description": "CaptureController.prototype.decreaseZoomLevel steps the captured tab to the previous supported zoom level.",
      "kind": "typeof",
      "test": "CaptureController.prototype.decreaseZoomLevel",
      "expect": "function",
      "specSection": "https://w3c.github.io/mediacapture-surface-control/#dom-capturecontroller-decreasezoomlevel"
    },
    {
      "id": "reset-zoom-level-is-function",
      "description": "CaptureController.prototype.resetZoomLevel resets the captured tab to 100 percent zoom.",
      "kind": "typeof",
      "test": "CaptureController.prototype.resetZoomLevel",
      "expect": "function",
      "specSection": "https://w3c.github.io/mediacapture-surface-control/#dom-capturecontroller-resetzoomlevel"
    },
    {
      "id": "onzoomlevelchange-handler",
      "description": "CaptureController exposes an onzoomlevelchange event handler attribute.",
      "kind": "script",
      "test": "(()=>typeof CaptureController==='function'&&'onzoomlevelchange' in CaptureController.prototype)()",
      "specSection": "https://w3c.github.io/mediacapture-surface-control/#dom-capturecontroller-onzoomlevelchange"
    }
  ]
}
