{
  "release": "v146",
  "featureSlug": "uber-demo",
  "chromestatusId": 5181996801982464,
  "specUrl": "https://drafts.csswg.org/css-animations-2/#timeline-triggers",
  "generatedAt": "2026-06-02T08:08:51Z",
  "author": "conformance-author-codex",
  "assertions": [
    {
      "id": "animation-trigger-behavior-once",
      "description": "animation-trigger-behavior: once is supported for scroll-triggered feed effects.",
      "kind": "css-supports",
      "test": "animation-trigger-behavior: once",
      "specSection": "https://drafts.csswg.org/css-animations-2/#animation-trigger"
    },
    {
      "id": "text-indent-hanging-each-line",
      "description": "text-indent accepts hanging and each-line together for editorial pull quotes.",
      "kind": "css-supports",
      "test": "text-indent: 2em hanging each-line",
      "specSection": "https://drafts.csswg.org/css-text/#text-indent-property"
    },
    {
      "id": "sanitizer-interface-exposed",
      "description": "Sanitizer is exposed for safe user-generated content insertion.",
      "kind": "exists",
      "test": "Sanitizer",
      "specSection": "https://wicg.github.io/sanitizer-api/"
    },
    {
      "id": "element-sethtml-exposed",
      "description": "Element.prototype.setHTML is available for sanitized HTML insertion.",
      "kind": "typeof",
      "test": "Element.prototype.setHTML",
      "expect": "function",
      "specSection": "https://wicg.github.io/sanitizer-api/#dom-element-sethtml"
    },
    {
      "id": "iterator-concat-exposed",
      "description": "Iterator.concat is exposed for sequencing feed content sources.",
      "kind": "typeof",
      "test": "Iterator.concat",
      "expect": "function",
      "specSection": "https://tc39.es/proposal-iterator-sequencing/"
    },
    {
      "id": "audiocontext-playbackstats",
      "description": "AudioContext instances expose playbackStats for monitoring fallback audio frames.",
      "kind": "script",
      "test": "(()=>{try{const Ctx=window.AudioContext||window.webkitAudioContext;if(!Ctx)return false;const ac=new Ctx();const ok='playbackStats' in ac;ac.close();return ok;}catch(_){return false;}})()",
      "specSection": "https://webaudio.github.io/web-audio-api/#AudioPlaybackStats"
    },
    {
      "id": "scoped-custom-element-registry-constructible",
      "description": "CustomElementRegistry is constructible for scoped custom element registries.",
      "kind": "script",
      "test": "(()=>{try{return new CustomElementRegistry() instanceof CustomElementRegistry;}catch(_){return false;}})()",
      "specSection": "https://html.spec.whatwg.org/multipage/custom-elements.html#customelementregistry"
    },
    {
      "id": "preferred-text-scale-env-supported",
      "description": "env(preferred-text-scale) is accepted in CSS for text scale aware typography.",
      "kind": "css-supports",
      "test": "font-size: calc(1rem * env(preferred-text-scale, 1))",
      "specSection": "https://drafts.csswg.org/css-fonts-5/#preferred-text-scale-env"
    }
  ]
}
