{
  "release": "v146",
  "featureSlug": "scroll-triggered-animations",
  "chromestatusId": 5181996801982464,
  "specUrl": "https://drafts.csswg.org/css-animations-2/#timeline-triggers",
  "generatedAt": "2026-06-01T08:00:00Z",
  "author": "conformance-author-v1-subagent",
  "assertions": [
    {
      "id": "animation-trigger-supported",
      "description": "The animation-trigger shorthand property is recognised by the parser.",
      "kind": "css-supports",
      "test": "animation-trigger: once"
    },
    {
      "id": "animation-trigger-behavior-once",
      "description": "animation-trigger-behavior accepts the 'once' keyword (play forward once when the trigger fires).",
      "kind": "css-supports",
      "test": "animation-trigger-behavior: once"
    },
    {
      "id": "animation-trigger-behavior-repeat",
      "description": "animation-trigger-behavior accepts the 'repeat' keyword (replay each time the trigger range is entered).",
      "kind": "css-supports",
      "test": "animation-trigger-behavior: repeat"
    },
    {
      "id": "animation-trigger-behavior-alternate",
      "description": "animation-trigger-behavior accepts 'alternate' — forward/reverse on enter/exit.",
      "kind": "css-supports",
      "test": "animation-trigger-behavior: alternate"
    },
    {
      "id": "animation-trigger-behavior-state",
      "description": "animation-trigger-behavior accepts 'state' — play forward on entry, reverse on exit, hold otherwise.",
      "kind": "css-supports",
      "test": "animation-trigger-behavior: state"
    },
    {
      "id": "animation-trigger-timeline-scroll",
      "description": "animation-trigger-timeline accepts scroll() as a timeline value.",
      "kind": "css-supports",
      "test": "animation-trigger-timeline: scroll()"
    },
    {
      "id": "animation-trigger-range-keywords",
      "description": "animation-trigger-range accepts named range keywords like 'entry' and 'exit'.",
      "kind": "css-supports",
      "test": "animation-trigger-range: entry 0% exit 100%"
    }
  ]
}
