{
  "release": "v144",
  "featureSlug": "performance-event-timing-interactioncount",
  "chromestatusId": 5153386492198912,
  "specUrl": "https://www.w3.org/TR/event-timing/#dom-performance-interactioncount",
  "generatedAt": "2026-06-01T08:03:56Z",
  "author": "conformance-author-v1-subagent",
  "assertions": [
    {
      "id": "interactionCount-exposed",
      "description": "performance.interactionCount is exposed on the Performance interface.",
      "kind": "script",
      "test": "'interactionCount' in performance",
      "specSection": "https://www.w3.org/TR/event-timing/#dom-performance-interactioncount"
    },
    {
      "id": "interactionCount-is-number",
      "description": "performance.interactionCount returns a number (unsigned long long).",
      "kind": "typeof",
      "test": "performance.interactionCount",
      "expect": "number",
      "specSection": "https://www.w3.org/TR/event-timing/#dom-performance-interactioncount"
    },
    {
      "id": "interactionCount-non-negative",
      "description": "Initial interactionCount is zero or higher; it must be a non-negative integer.",
      "kind": "script",
      "test": "performance.interactionCount >= 0",
      "specSection": "https://www.w3.org/TR/event-timing/#dom-performance-interactioncount"
    },
    {
      "id": "performance-event-timing-supported",
      "description": "PerformanceEventTiming is exposed — interactionCount complements event entries.",
      "kind": "exists",
      "test": "PerformanceEventTiming",
      "specSection": "https://www.w3.org/TR/event-timing/#sec-performance-event-timing"
    }
  ]
}
