{
  "release": "v149",
  "featureSlug": "selective-clipboard-format-read",
  "chromestatusId": 5203433409871872,
  "specUrl": "https://w3c.github.io/clipboard-apis/",
  "generatedAt": "2026-06-01T08:15:14Z",
  "author": "conformance-author-v1-subagent",
  "assertions": [
    {
      "id": "clipboard-read-exists",
      "description": "navigator.clipboard.read is a callable function returning ClipboardItem[].",
      "kind": "typeof",
      "test": "navigator.clipboard.read",
      "expect": "function",
      "specSection": "https://w3c.github.io/clipboard-apis/#dom-clipboard-read"
    },
    {
      "id": "clipboard-item-types-array",
      "description": "ClipboardItem.types is an array of strings (MIME types available without fetching data).",
      "kind": "script",
      "test": "(()=>{const c=new ClipboardItem({'text/plain': new Blob(['x'],{type:'text/plain'})});return c.types && typeof c.types.length === 'number' && c.types[0] === 'text/plain';})()",
      "specSection": "https://w3c.github.io/clipboard-apis/#dom-clipboarditem-types"
    },
    {
      "id": "clipboard-item-get-type-returns-promise",
      "description": "ClipboardItem.getType returns a Promise<Blob> (the lazily-fetched payload).",
      "kind": "script",
      "test": "(()=>{const c=new ClipboardItem({'text/plain': new Blob(['x'],{type:'text/plain'})});const p=c.getType('text/plain');return p && typeof p.then === 'function';})()",
      "specSection": "https://w3c.github.io/clipboard-apis/#dom-clipboarditem-gettype"
    },
    {
      "id": "clipboard-item-get-type-rejects-unknown",
      "description": "ClipboardItem.getType throws / rejects for a MIME type not in the available list.",
      "kind": "throws",
      "test": "new ClipboardItem({'text/plain': new Blob(['x'],{type:'text/plain'})}).getType('image/png')",
      "specSection": "https://w3c.github.io/clipboard-apis/#dom-clipboarditem-gettype"
    },
    {
      "id": "clipboard-read-text-still-supported",
      "description": "navigator.clipboard.readText remains as the simple text shortcut.",
      "kind": "typeof",
      "test": "navigator.clipboard.readText",
      "expect": "function",
      "specSection": "https://w3c.github.io/clipboard-apis/#dom-clipboard-readtext"
    },
    {
      "id": "permissions-clipboard-read-named",
      "description": "navigator.permissions can query 'clipboard-read' (the permission selective reads depend on).",
      "kind": "script",
      "test": "navigator.permissions && typeof navigator.permissions.query === 'function'",
      "specSection": "https://w3c.github.io/clipboard-apis/#privacy"
    }
  ]
}
