{
  "release": "v141",
  "featureSlug": "windowaudio-for-getdisplaymedia",
  "conceptSlug": "exclude-on-window",
  "chromestatusId": 5072779506089984,
  "reviewedAt": "2026-06-01T00:00:00Z",
  "reviewer": "reviewer-v1-subagent",
  "rubric": {
    "spec_match": {
      "state": "pass",
      "rationale": "Demo exercises the core API surface \u2014 every title keyword (getdisplaymedia, windowaudio) and 7 summary keywords appear directly in the page."
    },
    "interactive": {
      "state": "pass",
      "rationale": "Real interactive surface: 3 form controls wired to ~1492 chars of script that mutate the page state."
    },
    "blurb_alignment": {
      "state": "pass",
      "rationale": "Feature-index blurb and concept lede share 11 keywords; the page delivers what the index promises."
    },
    "edge_cases": {
      "state": "pass",
      "rationale": "Page feature-detects the API and shows both the supported and unsupported branches (try/catch + missing-API messaging)."
    },
    "references": {
      "state": "pass",
      "rationale": "Page links to https://chromestatus.com/feature/5072779506089984 directly in the see-also / references section."
    },
    "design_system": {
      "state": "pass",
      "rationale": "All colours flow through CSS variables, no raw hex, and button overrides keep colour and background in sync."
    }
  },
  "openQuestions": [],
  "summary": "Solid concept page: 6 of 6 rubric criteria pass, no fails. Minor follow-ups left as open questions."
}
