{
  "release": "v138",
  "featureSlug": "css-anchored-fallback-container-queries",
  "chromestatusId": 5177580990496768,
  "specUrl": "https://drafts.csswg.org/css-anchor-position-2/#anchored-container-queries",
  "generatedAt": "2026-06-01T09:05:00Z",
  "author": "conformance-author-v1-subagent",
  "assertions": [
    {
      "id": "anchor-name-supported",
      "description": "Anchor positioning baseline: anchor-name is supported (prereq for anchored fallback queries).",
      "kind": "css-supports",
      "test": "anchor-name: --foo",
      "specSection": "https://drafts.csswg.org/css-anchor-position-1/#name"
    },
    {
      "id": "position-try-fallbacks-supported",
      "description": "position-try-fallbacks is supported — without fallbacks, anchored() queries have nothing to match against.",
      "kind": "css-supports",
      "test": "position-try-fallbacks: flip-block",
      "specSection": "https://drafts.csswg.org/css-anchor-position-1/#fallback-property"
    },
    {
      "id": "anchored-fallback-container-query-parses",
      "description": "@container anchored(fallback) is a valid container query condition syntax.",
      "kind": "script",
      "test": "(()=>{const s=document.createElement('style');s.textContent='@container anchored(fallback) { .x { color: red; } }';document.head.appendChild(s);const ok=s.sheet&&s.sheet.cssRules.length>0;s.remove();return ok;})()",
      "specSection": "https://drafts.csswg.org/css-anchor-position-2/#anchored-container-queries"
    },
    {
      "id": "container-type-anchored-supported",
      "description": "container-type accepts 'anchored' so an element can be queried for anchored fallback state.",
      "kind": "css-supports",
      "test": "container-type: anchored",
      "specSection": "https://drafts.csswg.org/css-anchor-position-2/#anchored-container-queries"
    },
    {
      "id": "css-supports-anchored-container-query",
      "description": "CSS.supports recognises the @container anchored() at-rule shape.",
      "kind": "script",
      "test": "CSS.supports('selector(:has(*))') && (()=>{const s=document.createElement('style');s.textContent='@container anchored(--anchor fallback) {}';document.head.appendChild(s);const ok=!!s.sheet;s.remove();return ok;})()",
      "specSection": "https://drafts.csswg.org/css-anchor-position-2/#anchored-container-queries"
    }
  ]
}
