{
  "release": "v150",
  "featureSlug": "programmatic-scroll-promises",
  "conceptSlug": "virtual-tour",
  "chromestatusId": 5082138340491264,
  "reviewedAt": "2026-06-01T22:21:24Z",
  "reviewer": "v150-reviewer-subagent",
  "rubric": {
    "spec_match": {
      "state": "pass",
      "rationale": "Stellar presentation of await scrollTo sequencing, ensuring each stop resolves before progress indicator moves."
    },
    "interactive": {
      "state": "pass",
      "rationale": "Excellent. Has start, reset, interactive step badges, a progress dot row, dynamic log, and active insight summaries."
    },
    "blurb_alignment": {
      "state": "pass",
      "rationale": "Fully matches the parent guided 5-stop listing."
    },
    "edge_cases": {
      "state": "pass",
      "rationale": "Features custom smooth scroll animation fallbacks for older clients."
    },
    "references": {
      "state": "fail",
      "rationale": "Violates the hard rule from AGENTS.md: lacks a canonical chromestatus.com reference link on the concept page."
    },
    "design_system": {
      "state": "pass",
      "rationale": "Sleek tour console using neat border wraps, a visual progress dot container, and mono fonts."
    }
  },
  "openQuestions": [
    {
      "title": "Missing ChromeStatus Link",
      "detail": "Add the canonical ChromeStatus link (https://chromestatus.com/feature/5082138340491264) to the see also or references list to comply with AGENTS.md hard rules.",
      "severity": "moderate"
    }
  ]
}
